[{"Case_Count":0.0,"Events":null,"Country":"Jordan","State":"Madaba","Event_Date":"2015-05-01","Event_ID":"CU_Count_Madaba_2015-05-01","Event_Type":"Civil Unrest"},{"Case_Count":0.0,"Events":null,"Country":"Jordan","State":"Madaba","Event_Date":"2015-06-01","Event_ID":"CU_Count_Madaba_2015-06-01","Event_Type":"Civil Unrest"},{"Case_Count":3.0,"Events":["CU4894","CU4898","CU4914"],"Country":"Jordan","State":"Madaba","Event_Date":"2015-07-01","Event_ID":"CU_Count_Madaba_2015-07-01","Event_Type":"Civil Unrest"},{"Case_Count":5.0,"Events":["CU5452","CU5453","CU5445","CU5443","CU5448"],"Country":"Jordan","State":"Madaba","Event_Date":"2015-08-01","Event_ID":"CU_Count_Madaba_2015-08-01","Event_Type":"Civil Unrest"},{"Case_Count":2.0,"Events":["CU5803","CU5827"],"Country":"Jordan","State":"Madaba","Event_Date":"2015-09-01","Event_ID":"CU_Count_Madaba_2015-09-01","Event_Type":"Civil Unrest"},{"Case_Count":6.0,"Events":["CU9777","CU9764","CU9763","CU9811","CU9819","CU9737"],"Country":"Jordan","State":"Madaba","Event_Date":"2015-10-01","Event_ID":"CU_Count_Madaba_2015-10-01","Event_Type":"Civil Unrest"},{"Case_Count":4.0,"Events":["CU14126","CU14123","CU14125","CU14108"],"Country":"Jordan","State":"Madaba","Event_Date":"2015-11-01","Event_ID":"CU_Count_Madaba_2015-11-01","Event_Type":"Civil Unrest"},{"Case_Count":4.0,"Events":["CU36586","CU36603","CU36553","CU36552"],"Country":"Jordan","State":"Madaba","Event_Date":"2015-12-01","Event_ID":"CU_Count_Madaba_2015-12-01","Event_Type":"Civil Unrest"},{"Case_Count":1.0,"Events":["CU43351"],"Country":"Jordan","State":"Madaba","Event_Date":"2016-01-01","Event_ID":"CU_Count_Madaba_2016-01-01","Event_Type":"Civil Unrest"},{"Case_Count":0.0,"Events":null,"Country":"Jordan","State":"Madaba","Event_Date":"2016-02-01","Event_ID":"CU_Count_Madaba_2016-02-01","Event_Type":"Civil Unrest"},{"Case_Count":3.0,"Events":["CU47278","CU47279","CU47280"],"Country":"Jordan","State":"Madaba","Event_Date":"2016-03-01","Event_ID":"CU_Count_Madaba_2016-03-01","Event_Type":"Civil Unrest"},{"Case_Count":4.0,"Events":["CU51411","CU51565","CU51784","CU51752"],"Country":"Jordan","State":"Madaba","Event_Date":"2016-04-01","Event_ID":"CU_Count_Madaba_2016-04-01","Event_Type":"Civil Unrest"},{"Case_Count":4.0,"Events":["CU52241","CU52291","CU52320","CU52697"],"Country":"Jordan","State":"Madaba","Event_Date":"2016-05-01","Event_ID":"CU_Count_Madaba_2016-05-01","Event_Type":"Civil Unrest"},{"Case_Count":5.0,"Events":["CU52923","CU53079","CU52874","CU52807","CU53103"],"Country":"Jordan","State":"Madaba","Event_Date":"2016-06-01","Event_ID":"CU_Count_Madaba_2016-06-01","Event_Type":"Civil Unrest"},{"Case_Count":14.0,"Events":["CU53144","CU53142","CU53231","CU53267","CU53286","CU53379","CU53127","CU53227","CU53294","CU53344","CU53226","CU53171","CU53181","CU53166"],"Country":"Jordan","State":"Madaba","Event_Date":"2016-07-01","Event_ID":"CU_Count_Madaba_2016-07-01","Event_Type":"Civil Unrest"},{"Case_Count":1.0,"Events":["CU53541"],"Country":"Jordan","State":"Madaba","Event_Date":"2016-08-01","Event_ID":"CU_Count_Madaba_2016-08-01","Event_Type":"Civil Unrest"},{"Case_Count":3.0,"Events":["CU53829","CU53804","CU53738"],"Country":"Jordan","State":"Madaba","Event_Date":"2016-09-01","Event_ID":"CU_Count_Madaba_2016-09-01","Event_Type":"Civil Unrest"},{"Case_Count":2.0,"Events":["CU54201","CU54322"],"Country":"Jordan","State":"Madaba","Event_Date":"2016-10-01","Event_ID":"CU_Count_Madaba_2016-10-01","Event_Type":"Civil Unrest"},{"Case_Count":0.0,"Events":null,"Country":"Jordan","State":"Madaba","Event_Date":"2016-11-01","Event_ID":"CU_Count_Madaba_2016-11-01","Event_Type":"Civil Unrest"},{"Case_Count":1.0,"Events":["CU55018"],"Country":"Jordan","State":"Madaba","Event_Date":"2016-12-01","Event_ID":"CU_Count_Madaba_2016-12-01","Event_Type":"Civil Unrest"},{"Case_Count":0.0,"Events":null,"Country":"Jordan","State":"Madaba","Event_Date":"2017-01-01","Event_ID":"CU_Count_Madaba_2017-01-01","Event_Type":"Civil Unrest"},{"Case_Count":0.0,"Events":null,"Country":"Jordan","State":"Madaba","Event_Date":"2017-02-01","Event_ID":"CU_Count_Madaba_2017-02-01","Event_Type":"Civil Unrest"},{"Case_Count":4.0,"Events":["CU55542","CU55466","CU55465","CU55512"],"Country":"Jordan","State":"Madaba","Event_Date":"2017-03-01","Event_ID":"CU_Count_Madaba_2017-03-01","Event_Type":"Civil Unrest"},{"Case_Count":0.0,"Events":null,"Country":"Jordan","State":"Madaba","Event_Date":"2017-04-01","Event_ID":"CU_Count_Madaba_2017-04-01","Event_Type":"Civil Unrest"},{"Case_Count":2.0,"Events":["CU55991","CU55962"],"Country":"Jordan","State":"Madaba","Event_Date":"2017-05-01","Event_ID":"CU_Count_Madaba_2017-05-01","Event_Type":"Civil Unrest"},{"Case_Count":2.0,"Events":["CU56141","CU56105"],"Country":"Jordan","State":"Madaba","Event_Date":"2017-06-01","Event_ID":"CU_Count_Madaba_2017-06-01","Event_Type":"Civil Unrest"},{"Case_Count":1.0,"Events":["CU56394"],"Country":"Jordan","State":"Madaba","Event_Date":"2017-07-01","Event_ID":"CU_Count_Madaba_2017-07-01","Event_Type":"Civil Unrest"},{"Case_Count":0.0,"Events":null,"Country":"Jordan","State":"Madaba","Event_Date":"2017-08-01","Event_ID":"CU_Count_Madaba_2017-08-01","Event_Type":"Civil Unrest"},{"Case_Count":3.0,"Events":["CU56689","CU56691","CU56738"],"Country":"Jordan","State":"Madaba","Event_Date":"2017-09-01","Event_ID":"CU_Count_Madaba_2017-09-01","Event_Type":"Civil Unrest"},{"Case_Count":0.0,"Events":null,"Country":"Jordan","State":"Madaba","Event_Date":"2017-10-01","Event_ID":"CU_Count_Madaba_2017-10-01","Event_Type":"Civil Unrest"},{"Case_Count":0.0,"Events":null,"Country":"Jordan","State":"Madaba","Event_Date":"2017-11-01","Event_ID":"CU_Count_Madaba_2017-11-01","Event_Type":"Civil Unrest"},{"Case_Count":6.0,"Events":["CU57089","CU57111","CU57289","CU57475","CU57395","CU57358"],"Country":"Jordan","State":"Madaba","Event_Date":"2017-12-01","Event_ID":"CU_Count_Madaba_2017-12-01","Event_Type":"Civil Unrest"},{"Case_Count":2.0,"Events":["CU57664","CU57613"],"Country":"Jordan","State":"Madaba","Event_Date":"2018-01-01","Event_ID":"CU_Count_Madaba_2018-01-01","Event_Type":"Civil Unrest"},{"Case_Count":4.0,"Events":["CU58006","CU57739","CU57724","CU57981"],"Country":"Jordan","State":"Madaba","Event_Date":"2018-02-01","Event_ID":"CU_Count_Madaba_2018-02-01","Event_Type":"Civil Unrest"},{"Case_Count":3.0,"Events":["CU58167","CU58037","CU58220"],"Country":"Jordan","State":"Madaba","Event_Date":"2018-03-01","Event_ID":"CU_Count_Madaba_2018-03-01","Event_Type":"Civil Unrest"},{"Case_Count":0.0,"Events":null,"Country":"Jordan","State":"Madaba","Event_Date":"2018-04-01","Event_ID":"CU_Count_Madaba_2018-04-01","Event_Type":"Civil Unrest"},{"Case_Count":4.0,"Events":["CU60079","CU60189","CU60052","CU60028"],"Country":"Jordan","State":"Madaba","Event_Date":"2018-05-01","Event_ID":"CU_Count_Madaba_2018-05-01","Event_Type":"Civil Unrest"},{"Case_Count":5.0,"Events":["CU60282","CU60338","CU60337","CU60352","CU60375"],"Country":"Jordan","State":"Madaba","Event_Date":"2018-06-01","Event_ID":"CU_Count_Madaba_2018-06-01","Event_Type":"Civil Unrest"},{"Case_Count":0.0,"Events":null,"Country":"Jordan","State":"Madaba","Event_Date":"2018-07-01","Event_ID":"CU_Count_Madaba_2018-07-01","Event_Type":"Civil Unrest"},{"Case_Count":0.0,"Events":null,"Country":"Jordan","State":"Madaba","Event_Date":"2018-08-01","Event_ID":"CU_Count_Madaba_2018-08-01","Event_Type":"Civil Unrest"},{"Case_Count":2.0,"Events":["CU60723","CU60712"],"Country":"Jordan","State":"Madaba","Event_Date":"2018-09-01","Event_ID":"CU_Count_Madaba_2018-09-01","Event_Type":"Civil Unrest"},{"Case_Count":9.0,"Events":["CU60978","CU61042","CU61283","CU61287","CU61284","CU61286","CU61285","CU61288","CU61281"],"Country":"Jordan","State":"Madaba","Event_Date":"2018-10-01","Event_ID":"CU_Count_Madaba_2018-10-01","Event_Type":"Civil Unrest"},{"Case_Count":3.0,"Events":["CU61576","CU61514","CU61517"],"Country":"Jordan","State":"Madaba","Event_Date":"2018-11-01","Event_ID":"CU_Count_Madaba_2018-11-01","Event_Type":"Civil Unrest"},{"Case_Count":3.0,"Events":["CU61688","CU61659","CU61677"],"Country":"Jordan","State":"Madaba","Event_Date":"2018-12-01","Event_ID":"CU_Count_Madaba_2018-12-01","Event_Type":"Civil Unrest"}]