{
  "participant_id": "Mercury_Baserate",
  "payload": [
    {
      "Event_Date": "2018-09-24",
      "timestamp": "2018-09-22T16:20:12.0",
      "Event_Subtype": "Conflict",
      "Actor": "Egyptian Military",
      "City": "Bi’r al ‘Abd",
      "Latitude": 31.0189,
      "Longitude": 33.0098,
      "State": "Shamāl Sīnāʼ",
      "Country": "Egypt",
      "Event_Type": "Military Activity",
      "Warning_ID": "Mercury_Baserate5e620b352e514c99ab7f364ceade871f"
    },
    {
      "Event_Date": "2018-10-01",
      "timestamp": "2018-09-26T22:14:43.0",
      "Event_Subtype": "Conflict",
      "Actor": "Egyptian Police",
      "City": "‘Izbat Umm ash Shu‘ūr",
      "Latitude": 31.3059,
      "Longitude": 31.1898,
      "State": "Kafr ash Shaykh",
      "Country": "Egypt",
      "Event_Type": "Military Activity",
      "Warning_ID": "Mercury_Baserate3e0f362225ad4d0990672194b68d2be1"
    },
    {
      "Event_Date": "2018-10-01",
      "timestamp": "2018-09-25T15:47:8.0",
      "Event_Subtype": "Conflict",
      "Actor": "Egyptian Military",
      "City": "Muḩāfaz̧at Shamāl Sīnā’",
      "Latitude": 30.5,
      "Longitude": 33.7,
      "State": "Shamāl Sīnāʼ",
      "Country": "Egypt",
      "Event_Type": "Military Activity",
      "Warning_ID": "Mercury_Baserate9c3693fbd7784ea6b75a705f63ab0e88"
    },
    {
      "Event_Date": "2018-10-01",
      "timestamp": "2018-09-27T4:52:5.0",
      "Event_Subtype": "Conflict",
      "Actor": "Egyptian Military",
      "City": "Al Qalyūbīyah",
      "Latitude": 31.1124,
      "Longitude": 31.5687,
      "State": "Muḩāfaz̧at ad Daqahlīyah",
      "Country": "Egypt",
      "Event_Type": "Military Activity",
      "Warning_ID": "Mercury_Baseratebb102955f2a54fbdb1bd645451cdc85c"
    },
    {
      "Event_Date": "2018-09-30",
      "timestamp": "2018-09-26T20:42:54.0",
      "Event_Subtype": "Force Posture",
      "Actor": "Egyptian Police",
      "City": "Asyūţ",
      "Latitude": 27.181,
      "Longitude": 31.1837,
      "State": "Asyūţ",
      "Country": "Egypt",
      "Event_Type": "Military Activity",
      "Warning_ID": "Mercury_Baserate1253aa47d6dd4ffdadc80db32238986e"
    },
    {
      "Event_Date": "2018-09-20",
      "timestamp": "2018-09-13T5:3:27.0",
      "Event_Subtype": "Force Posture",
      "Actor": "Egyptian Military",
      "City": "Muḩāfaz̧at Shamāl Sīnā’",
      "Latitude": 30.5,
      "Longitude": 33.7,
      "State": "Shamāl Sīnāʼ",
      "Country": "Egypt",
      "Event_Type": "Military Activity",
      "Warning_ID": "Mercury_Baserate1c6a16c73a164c81b3addf3662961a8a"
    },
    {
      "Event_Date": "2018-09-28",
      "timestamp": "2018-09-22T9:26:19.0",
      "Event_Subtype": "Conflict",
      "Actor": "Egyptian Military",
      "City": "Muḩāfaz̧at Shamāl Sīnā’",
      "Latitude": 30.5,
      "Longitude": 33.7,
      "State": "Shamāl Sīnāʼ",
      "Country": "Egypt",
      "Event_Type": "Military Activity",
      "Warning_ID": "Mercury_Baseratef614cd194f124b31b466a5a4333c3f13"
    },
    {
      "Event_Date": "2018-09-21",
      "timestamp": "2018-09-12T3:43:3.0",
      "Event_Subtype": "Force Posture",
      "Actor": "Egyptian Police",
      "City": "Kafr as Sallāmīyah",
      "Latitude": 30.5051,
      "Longitude": 31.1235,
      "State": "Muḩāfaz̧at al Minūfīyah",
      "Country": "Egypt",
      "Event_Type": "Military Activity",
      "Warning_ID": "Mercury_Baserate3de7ecc703c24dfea37184eb310ede0f"
    },
    {
      "Event_Date": "2018-09-30",
      "timestamp": "2018-09-29T6:19:47.0",
      "Event_Subtype": "Conflict",
      "Actor": "Egyptian Military",
      "City": "Madīnat as Sādis min Uktūbar",
      "Latitude": 29.9464,
      "Longitude": 30.9169,
      "State": "Al Jīzah",
      "Country": "Egypt",
      "Event_Type": "Military Activity",
      "Warning_ID": "Mercury_Baserate2ed6c5928c7a4c2a90ec44a001238422"
    },
    {
      "Event_Date": "2018-09-24",
      "timestamp": "2018-09-17T21:10:57.0",
      "Event_Subtype": "Conflict",
      "Actor": "Egyptian Police",
      "City": "Muḩāfaz̧at Shamāl Sīnā’",
      "Latitude": 30.5,
      "Longitude": 33.7,
      "State": "Shamāl Sīnāʼ",
      "Country": "Egypt",
      "Event_Type": "Military Activity",
      "Warning_ID": "Mercury_Baserate54c1c3482a6743078c9795017dac3015"
    }
  ]
}